link/__init__.py
etna_link-0.0.6.dist-info/METADATA
etna_link-0.0.6.dist-info/WHEEL
etna_link-0.0.6.dist-info/top_level.txt
etna_link-0.0.6.dist-info/RECORD
