Metadata-Version: 2.1
Name: etna-link
Version: 0.0.6
Summary: Python wrapper to inspect the C AST produced by clang
Home-page: https://github.com/etna-alternance/link
Author: Clément Doumergue
Author-email: clement.doumergue@etna.io
License: UNKNOWN
Platform: UNKNOWN
Classifier: Programming Language :: Python :: 3
Classifier: License :: OSI Approved :: MIT License
Classifier: Operating System :: OS Independent
Requires-Dist: clang
